{
    "Keys":
    [
        "`","1","2","3","4","5","6","7","8","9","0","-","=",
        "q","w","e","r","t","y","u","i","o","p","[","]","\\",
        "a","s","d","f","g","h","j","k","l",";","'",
        "z","x","c","v","b","n","m",",",".","/","shift"
    ],

    "Mapping":
    {
        "`":"`",
        "1":"1",
        "2":"2",
        "3":"3",
        "4":"4",
        "5":"5",
        "6":"6",
        "7":"7",
        "8":"8",
        "9":"9",
        "0":"0",
        "-":"-",
        "=":"=",

        "~":"`",
        "!":"1",
        "@":"2",
        "#":"3",
        "$":"4",
        "%":"5",
        "^":"6",
        "&":"7",
        "*":"8",
        "(":"9",
        ")":"0",
        "_":"-",
        "+":"=",

        "q":"q",
        "w":"w",
        "e":"e",
        "r":"r",
        "t":"t",
        "y":"y",
        "u":"u",
        "i":"i",
        "o":"o",
        "p":"p",
        "[":"[",
        "]":"]",
        "\\":"\\",

        "Q":"q",
        "W":"w",
        "E":"e",
        "R":"r",
        "T":"t",
        "Y":"y",
        "U":"u",
        "I":"i",
        "O":"o",
        "P":"p",
        "{":"[",
        "}":"]",
        "|":"\\",

        "a":"a",
        "s":"s",
        "d":"d",
        "f":"f",
        "g":"g",
        "h":"h",
        "j":"j",
        "k":"k",
        "l":"l",
        ";":";",
        "'":"'",

        "A":"a",
        "S":"s",
        "D":"d",
        "F":"f",
        "G":"g",
        "H":"h",
        "J":"j",
        "K":"k",
        "L":"l",
        ":":";",
        "\"":"'",

        "z":"z",
        "x":"x",
        "c":"c",
        "v":"v",
        "b":"b",
        "n":"n",
        "m":"m",
        ",":",",
        ".":".",
        "/":"/",

        "Z":"z",
        "X":"x",
        "C":"c",
        "V":"v",
        "B":"b",
        "N":"n",
        "M":"m",
        "<":",",
        ">":".",
        "?":"/"

    },

    "Cases":
    {
        "Upper":    [
            "~","!","@","#","$","%","^","&","*","(",")","_","+",
            "Q","W","E","R","T","Y","U","I","O","P","{","}","|",
            "A","S","D","F","G","H","J","K","L",":","\"",
            "Z","X","C","V","B","N","M","<",">","?"
        ],
        "Lower":    [
            "`","1","2","3","4","5","6","7","8","9","0","-","=",
            "q","w","e","r","t","y","u","i","o","p","[","]","\\",
            "a","s","d","f","g","h","j","k","l",";","'",
            "z","x","c","v","b","n","m",",",".","/"
        ]
    },

    "Finger-Assignment":
    {
        "`":"little","1":"little","q":"little","a":"little","z":"little","0":"little","p":"little",";":"little","/":"little","-":"little","[":"little","'":"little","=":"little","]":"little","\\":"little","shift":"little",
        
        "2":"ring","w":"ring","s":"ring","x":"ring","9":"ring","o":"ring","l":"ring",".":"ring",
        
        "3":"middle","e":"middle","d":"middle","c":"middle","8":"middle","i":"middle","k":"middle",",":"middle",
        
        "4":"index","r":"index","f":"index","v":"index","5":"index","t":"index","g":"index","b":"index","6":"index","y":"index","h":"index","n":"index","7":"index","u":"index","j":"index","m":"index"
    },

    "Hand-Assignment":
    {
        "`":"left","1":"left","q":"left","a":"left","z":"left","2":"left","w":"left","s":"left","x":"left","3":"left","e":"left","d":"left","c":"left","4":"left","r":"left","f":"left","v":"left","5":"left","t":"left","g":"left","b":"left","shift":"left",
        "6":"right","y":"right","h":"right","n":"right","7":"right","u":"right","j":"right","m":"right","8":"right","i":"right","k":"right",",":"right","9":"right","o":"right","l":"right",".":"right","0":"right","p":"right",";":"right","/":"right","-":"right","[":"right","'":"right","=":"right","]":"right","\\":"right"
    },

    "Distance":{
        "`":5.0,
        "1":5.0,
        "2":4.0,
        "3":4.0,
        "4":4.0,
        "5":3.5,
        "6":4.5,
        "7":4.0,
        "8":4.0,
        "9":4.0,
        "0":4.0,
        "-":4.0,
        "=":4.5,

        "q":2.0,
        "w":2.0,
        "e":2.0,
        "r":2.0,
        "t":2.5,
        "y":3.0,
        "u":2.0,
        "i":2.0,
        "o":2.0,
        "p":2.0,
        "[":2.5,
        "]":4.0,
        "\\":5.0,

        "a":0.0,
        "s":0.0,
        "d":0.0,
        "f":0.0,
        "g":2.0,
        "h":2.0,
        "j":0.0,
        "k":0.0,
        "l":0.0,
        ";":0.0,
        "'":2.0,

        "z":2.0,
        "x":2.0,
        "c":2.0,
        "v":2.0,
        "b":3.5,
        "n":2.0,
        "m":2.0,
        ",":2.0,
        ".":2.0,
        "/":2.0
    }
}